pandots/__init__.py
pandots/pandots.py
pandots-0.0.4.dist-info/LICENSE
pandots-0.0.4.dist-info/METADATA
pandots-0.0.4.dist-info/WHEEL
pandots-0.0.4.dist-info/entry_points.txt
pandots-0.0.4.dist-info/top_level.txt
pandots-0.0.4.dist-info/RECORD
