Metadata-Version: 2.1
Name: pandots
Version: 0.0.4
Summary: Pangenome dotplot
Author-email: Allen Mamerto <amamerto@salk.edu>
Project-URL: Homepage, https://gitlab.com/salk-tm/pandots
Project-URL: Documentation, https://salk-tm.gitlab.io/pandots
Classifier: Programming Language :: Python :: 3
Classifier: Operating System :: OS Independent
Classifier: License :: OSI Approved :: BSD License
Requires-Python: >=3.10
License-File: LICENSE
Requires-Dist: pandas
Requires-Dist: numpy
Requires-Dist: seaborn
Requires-Dist: plotnine ==0.12.4
